Workbook

Sheet Riepilogo
A1: RIEPILOGO FATTURE LEASING – FLOTTA AZIENDALE
A3: Ciclo | B3: N° Fattura | C3: Periodo | D3: N° Veicoli | E3: Totale Canoni (€) | F3: Totale Extra km (€) | G3: Totale Fattura (€)
A4: Ciclo 1 – Apr 2025 | B4: LEASE-2025-004 | C4: 01/04/2025 – 30/04/2025 | D4: 50 | E4: ='Ciclo 1'!D55 -> 19205 | F4: ='Ciclo 1'!H55 -> 1165.44 | G4: ='Ciclo 1'!I55 -> 20370.44
A5: Ciclo 2 – Mag 2025 | B5: LEASE-2025-005 | C5: 01/05/2025 – 31/05/2025 | D5: 50 | E5: ='Ciclo 2'!D55 -> 19205 | F5: ='Ciclo 2'!H55 -> 1193.76 | G5: ='Ciclo 2'!I55 -> 20398.76
A6: Ciclo 3 – Giu 2025 | B6: LEASE-2025-006 | C6: 01/06/2025 – 30/06/2025 | D6: 50 | E6: ='Ciclo 3'!D55 -> 19205 | F6: ='Ciclo 3'!H55 -> 1083.72 | G6: ='Ciclo 3'!I55 -> 20288.72
A7: TOTALE COMPLESSIVO | E7: =SUM(E4:E6) -> 57615 | F7: =SUM(F4:F6) -> 3442.92 | G7: =SUM(G4:G6) -> 61057.92

Sheet Ciclo 1
A1: FATTURA LEASING FLOTTA – Ciclo 1 – Apr 2025 – N° LEASE-2025-004
A2: Periodo competenza: 01/04/2025 – 30/04/2025 | Scadenza pagamento: 30/05/2025 | Costo extra km: € 0.12/km
A4: Targa | B4: Modello | C4: Anno | D4: Canone Mensile (€) | E4: KM Contrattuali | F4: KM Percorsi | G4: KM Extra | H4: Costo Extra (€) | I4: Totale Riga (€)
A5: FL123AB | B5: Fiat Doblò Cargo 1.6 MJT | C5: 2021 | D5: 320 | E5: 2000 | F5: 1818 | G5: =MAX(0,F5-E5) -> 0 | H5: =G5*0.12 -> 0 | I5: =D5+H5 -> 320
A6: FL456CD | B6: Volkswagen Transporter T6 2.0 TDI | C6: 2020 | D6: 480 | E6: 2000 | F6: 2211 | G6: =MAX(0,F6-E6) -> 211 | H6: =G6*0.12 -> 25.32 | I6: =D6+H6 -> 505.32
A7: FL789EF | B7: Ford Transit Custom 2.0 EcoBlue | C7: 2022 | D7: 440 | E7: 2000 | F7: 1658 | G7: =MAX(0,F7-E7) -> 0 | H7: =G7*0.12 -> 0 | I7: =D7+H7 -> 440
A8: FL321GH | B8: Renault Trafic 1.6 dCi | C8: 2019 | D8: 370 | E8: 2000 | F8: 1529 | G8: =MAX(0,F8-E8) -> 0 | H8: =G8*0.12 -> 0 | I8: =D8+H8 -> 370
A9: FL654IJ | B9: Fiat Fiorino 1.3 MJT | C9: 2021 | D9: 230 | E9: 2000 | F9: 1325 | G9: =MAX(0,F9-E9) -> 0 | H9: =G9*0.12 -> 0 | I9: =D9+H9 -> 230
A10: FL987KL | B10: Mercedes-Benz Sprinter 314 CDI | C10: 2020 | D10: 620 | E10: 2000 | F10: 2557 | G10: =MAX(0,F10-E10) -> 557 | H10: =G10*0.12 -> 66.84 | I10: =D10+H10 -> 686.84
A11: FL147MN | B11: Peugeot Partner 1.5 BlueHDi | C11: 2022 | D11: 280 | E11: 2000 | F11: 2204 | G11: =MAX(0,F11-E11) -> 204 | H11: =G11*0.12 -> 24.48 | I11: =D11+H11 -> 304.48
A12: FL258OP | B12: Citroën Berlingo 1.5 BlueHDi | C12: 2021 | D12: 275 | E12: 2000 | F12: 2215 | G12: =MAX(0,F12-E12) -> 215 | H12: =G12*0.12 -> 25.8 | I12: =D12+H12 -> 300.8
A13: FL369QR | B13: Opel Vivaro 1.5 CDTI | C13: 2020 | D13: 390 | E13: 2000 | F13: 3382 | G13: =MAX(0,F13-E13) -> 1382 | H13: =G13*0.12 -> 165.84 | I13: =D13+H13 -> 555.84
A14: FL741ST | B14: Ford Transit 2.0 EcoBlue 130 | C14: 2019 | D14: 430 | E14: 2000 | F14: 1559 | G14: =MAX(0,F14-E14) -> 0 | H14: =G14*0.12 -> 0 | I14: =D14+H14 -> 430
A15: FL852UV | B15: Volkswagen Caddy 2.0 TDI | C15: 2022 | D15: 340 | E15: 2000 | F15: 1703 | G15: =MAX(0,F15-E15) -> 0 | H15: =G15*0.12 -> 0 | I15: =D15+H15 -> 340
A16: FL963WX | B16: Fiat Ducato 2.3 MJT 140 | C16: 2021 | D16: 410 | E16: 2000 | F16: 1384 | G16: =MAX(0,F16-E16) -> 0 | H16: =G16*0.12 -> 0 | I16: =D16+H16 -> 410
... A54: TO010UV | B54: Nissan Qashqai 1.5 dCi | C54: 2021 | D54: 385 | E54: 2000 | F54: 1180 | G54: =MAX(0,F54-E54) -> 0 | H54: =G54*0.12 -> 0 | I54: =D54+H54 -> 385
A55: TOTALE FATTURA | D55: =SUM(D5:D54) -> 19205 | G55: =SUM(G5:G54) -> 9712 | H55: =SUM(H5:H54) -> 1165.44 | I55: =SUM(I5:I54) -> 20370.44
A57: ⚠ Righe evidenziate in giallo = veicoli con sforamento chilometrico contrattuale

Sheet Ciclo 2
A1: FATTURA LEASING FLOTTA – Ciclo 2 – Mag 2025 – N° LEASE-2025-005
A2: Periodo competenza: 01/05/2025 – 31/05/2025 | Scadenza pagamento: 30/06/2025 | Costo extra km: € 0.12/km
A4: Targa | B4: Modello | C4: Anno | D4: Canone Mensile (€) | E4: KM Contrattuali | F4: KM Percorsi | G4: KM Extra | H4: Costo Extra (€) | I4: Totale Riga (€)
A5: FL123AB | B5: Fiat Doblò Cargo 1.6 MJT | C5: 2021 | D5: 320 | E5: 2000 | F5: 3791 | G5: =MAX(0,F5-E5) -> 1791 | H5: =G5*0.12 -> 214.92 | I5: =D5+H5 -> 534.92
A6: FL456CD | B6: Volkswagen Transporter T6 2.0 TDI | C6: 2020 | D6: 480 | E6: 2000 | F6: 1718 | G6: =MAX(0,F6-E6) -> 0 | H6: =G6*0.12 -> 0 | I6: =D6+H6 -> 480
A7: FL789EF | B7: Ford Transit Custom 2.0 EcoBlue | C7: 2022 | D7: 440 | E7: 2000 | F7: 1794 | G7: =MAX(0,F7-E7) -> 0 | H7: =G7*0.12 -> 0 | I7: =D7+H7 -> 440
A8: FL321GH | B8: Renault Trafic 1.6 dCi | C8: 2019 | D8: 370 | E8: 2000 | F8: 1637 | G8: =MAX(0,F8-E8) -> 0 | H8: =G8*0.12 -> 0 | I8: =D8+H8 -> 370
A9: FL654IJ | B9: Fiat Fiorino 1.3 MJT | C9: 2021 | D9: 230 | E9: 2000 | F9: 2607 | G9: =MAX(0,F9-E9) -> 607 | H9: =G9*0.12 -> 72.84 | I9: =D9+H9 -> 302.84
A10: FL987KL | B10: Mercedes-Benz Sprinter 314 CDI | C10: 2020 | D10: 620 | E10: 2000 | F10: 3085 | G10: =MAX(0,F10-E10) -> 1085 | H10: =G10*0.12 -> 130.2 | I10: =D10+H10 -> 750.2
A11: FL147MN | B11: Peugeot Partner 1.5 BlueHDi | C11: 2022 | D11: 280 | E11: 2000 | F11: 1212 | G11: =MAX(0,F11-E11) -> 0 | H11: =G11*0.12 -> 0 | I11: =D11+H11 -> 280
A12: FL258OP | B12: Citroën Berlingo 1.5 BlueHDi | C12: 2021 | D12: 275 | E12: 2000 | F12: 1522 | G12: =MAX(0,F12-E12) -> 0 | H12: =G12*0.12 -> 0 | I12: =D12+H12 -> 275
A13: FL369QR | B13: Opel Vivaro 1.5 CDTI | C13: 2020 | D13: 390 | E13: 2000 | F13: 1624 | G13: =MAX(0,F13-E13) -> 0 | H13: =G13*0.12 -> 0 | I13: =D13+H13 -> 390
A14: FL741ST | B14: Ford Transit 2.0 EcoBlue 130 | C14: 2019 | D14: 430 | E14: 2000 | F14: 1945 | G14: =MAX(0,F14-E14) -> 0 | H14: =G14*0.12 -> 0 | I14: =D14+H14 -> 430
A15: FL852UV | B15: Volkswagen Caddy 2.0 TDI | C15: 2022 | D15: 340 | E15: 2000 | F15: 3687 | G15: =MAX(0,F15-E15) -> 1687 | H15: =G15*0.12 -> 202.44 | I15: =D15+H15 -> 542.44
A16: FL963WX | B16: Fiat Ducato 2.3 MJT 140 | C16: 2021 | D16: 410 | E16: 2000 | F16: 1745 | G16: =MAX(0,F16-E16) -> 0 | H16: =G16*0.12 -> 0 | I16: =D16+H16 -> 410
... A54: TO010UV | B54: Nissan Qashqai 1.5 dCi | C54: 2021 | D54: 385 | E54: 2000 | F54: 1893 | G54: =MAX(0,F54-E54) -> 0 | H54: =G54*0.12 -> 0 | I54: =D54+H54 -> 385
A55: TOTALE FATTURA | D55: =SUM(D5:D54) -> 19205 | G55: =SUM(G5:G54) -> 9948 | H55: =SUM(H5:H54) -> 1193.76 | I55: =SUM(I5:I54) -> 20398.76
A57: ⚠ Righe evidenziate in giallo = veicoli con sforamento chilometrico contrattuale

Sheet Ciclo 3
A1: FATTURA LEASING FLOTTA – Ciclo 3 – Giu 2025 – N° LEASE-2025-006
A2: Periodo competenza: 01/06/2025 – 30/06/2025 | Scadenza pagamento: 30/07/2025 | Costo extra km: € 0.12/km
A4: Targa | B4: Modello | C4: Anno | D4: Canone Mensile (€) | E4: KM Contrattuali | F4: KM Percorsi | G4: KM Extra | H4: Costo Extra (€) | I4: Totale Riga (€)
A5: FL123AB | B5: Fiat Doblò Cargo 1.6 MJT | C5: 2021 | D5: 320 | E5: 2000 | F5: 1463 | G5: =MAX(0,F5-E5) -> 0 | H5: =G5*0.12 -> 0 | I5: =D5+H5 -> 320
A6: FL456CD | B6: Volkswagen Transporter T6 2.0 TDI | C6: 2020 | D6: 480 | E6: 2000 | F6: 1182 | G6: =MAX(0,F6-E6) -> 0 | H6: =G6*0.12 -> 0 | I6: =D6+H6 -> 480
A7: FL789EF | B7: Ford Transit Custom 2.0 EcoBlue | C7: 2022 | D7: 440 | E7: 2000 | F7: 1849 | G7: =MAX(0,F7-E7) -> 0 | H7: =G7*0.12 -> 0 | I7: =D7+H7 -> 440
A8: FL321GH | B8: Renault Trafic 1.6 dCi | C8: 2019 | D8: 370 | E8: 2000 | F8: 1919 | G8: =MAX(0,F8-E8) -> 0 | H8: =G8*0.12 -> 0 | I8: =D8+H8 -> 370
A9: FL654IJ | B9: Fiat Fiorino 1.3 MJT | C9: 2021 | D9: 230 | E9: 2000 | F9: 1430 | G9: =MAX(0,F9-E9) -> 0 | H9: =G9*0.12 -> 0 | I9: =D9+H9 -> 230
A10: FL987KL | B10: Mercedes-Benz Sprinter 314 CDI | C10: 2020 | D10: 620 | E10: 2000 | F10: 1273 | G10: =MAX(0,F10-E10) -> 0 | H10: =G10*0.12 -> 0 | I10: =D10+H10 -> 620
A11: FL147MN | B11: Peugeot Partner 1.5 BlueHDi | C11: 2022 | D11: 280 | E11: 2000 | F11: 1890 | G11: =MAX(0,F11-E11) -> 0 | H11: =G11*0.12 -> 0 | I11: =D11+H11 -> 280
A12: FL258OP | B12: Citroën Berlingo 1.5 BlueHDi | C12: 2021 | D12: 275 | E12: 2000 | F12: 1935 | G12: =MAX(0,F12-E12) -> 0 | H12: =G12*0.12 -> 0 | I12: =D12+H12 -> 275
A13: FL369QR | B13: Opel Vivaro 1.5 CDTI | C13: 2020 | D13: 390 | E13: 2000 | F13: 1101 | G13: =MAX(0,F13-E13) -> 0 | H13: =G13*0.12 -> 0 | I13: =D13+H13 -> 390
A14: FL741ST | B14: Ford Transit 2.0 EcoBlue 130 | C14: 2019 | D14: 430 | E14: 2000 | F14: 1111 | G14: =MAX(0,F14-E14) -> 0 | H14: =G14*0.12 -> 0 | I14: =D14+H14 -> 430
A15: FL852UV | B15: Volkswagen Caddy 2.0 TDI | C15: 2022 | D15: 340 | E15: 2000 | F15: 2908 | G15: =MAX(0,F15-E15) -> 908 | H15: =G15*0.12 -> 108.96 | I15: =D15+H15 -> 448.96
A16: FL963WX | B16: Fiat Ducato 2.3 MJT 140 | C16: 2021 | D16: 410 | E16: 2000 | F16: 1745 | G16: =MAX(0,F16-E16) -> 0 | H16: =G16*0.12 -> 0 | I16: =D16+H16 -> 410
... A54: TO010UV | B54: Nissan Qashqai 1.5 dCi | C54: 2021 | D54: 385 | E54: 2000 | F54: 1318 | G54: =MAX(0,F54-E54) -> 0 | H54: =G54*0.12 -> 0 | I54: =D54+H54 -> 385
A55: TOTALE FATTURA | D55: =SUM(D5:D54) -> 19205 | G55: =SUM(G5:G54) -> 9031 | H55: =SUM(H5:H54) -> 1083.72 | I55: =SUM(I5:I54) -> 20288.72
A57: ⚠ Righe evidenziate in giallo = veicoli con sforamento chilometrico contrattuale
